arspack/__init__.py
arspack-0.0.6.1.dist-info/LICENSE
arspack-0.0.6.1.dist-info/METADATA
arspack-0.0.6.1.dist-info/WHEEL
arspack-0.0.6.1.dist-info/entry_points.txt
arspack-0.0.6.1.dist-info/top_level.txt
arspack-0.0.6.1.dist-info/RECORD
