Metadata-Version: 2.1
Name: arspack
Version: 0.0.6.1
Summary: A Python Package Installer GUI powered by ArsTech.
Home-page: https://github.com/e500ky/arspack
Author: ArsTech
Author-email: arstechai@gmail.com
Classifier: Programming Language :: Python :: 3
Classifier: License :: OSI Approved :: MIT License
Classifier: Operating System :: OS Independent
Requires-Python: >=3.8
License-File: LICENSE
Requires-Dist: customtkinter
